{
    "status" : 0,
    "info" : "ok",
    "data" :{
        "page" :{
            "current_page":1,
            "total_page":3
        },
        "list" : [
            {   
                "userId" : "121",
                "userPhoto" : "http://7xjckn.com2.z0.glb.qiniucdn.com/2015-12-29_568257513df21.png",
                "realName" : "齐小吓",
                "positionName" : "会长",
                "registerCompany" : "浙江九鼎投资集团",
                "registerPosition" : "董事长",
                "industry" : "金融业",
                "groupName": "金融组",
                "userIntro" : "天生我材必有用，千金散尽还复来"
            },
            {
                "userId" : "128",
                "userPhoto" : "http://www.dreammove.cn/Uploads/Picture/2016-02-20/56c82e2051b1c.jpg",
                "realName" : "齐小吓",
                "positionName" : "会长",
                "registerCompany" : "浙江九鼎投资集团",
                "registerPosition" : "董事长",
                "industry" : "金融业",
                "groupName": "医疗组",
                "userIntro" : "天生我材必有用，千金散尽还复来"
            },
            {
                "userId" : "158",
                "userPhoto" : "http://7xjckn.com2.z0.glb.qiniucdn.com/2015-12-29_568257513df21.png",
                "realName" : "齐小吓",
                "positionName" : "会长",
                "registerCompany" : "浙江九鼎投资集团",
                "registerPosition" : "产品经理",
                "industry" : "计算机",
                "groupName": "金融组,医疗组",
                "userIntro" : "天生我材必有用，千金散尽还复来"
            },
            {
                "userId" : "221",
                "userPhoto" : "http://7xjckn.com2.z0.glb.qiniucdn.com/2015-12-29_568257513df21.png",
                "realName" : "齐小吓",
                "positionName" : "会长",
                "registerCompany" : "浙江九鼎投资集团",
                "registerPosition" : "总经理",
                "industry" : "计算机",
                "groupName": "",
                "userIntro" : "天生我材必有用，千金散尽还复来"
            }
        ]
    }
    
}